MANIFEST.in
README.txt
setup.cfg
setup.py
docs/HISTORY.txt
docs/LICENSE.GPL
docs/LICENSE.txt
raptus/__init__.py
raptus.supersized.egg-info/PKG-INFO
raptus.supersized.egg-info/SOURCES.txt
raptus.supersized.egg-info/dependency_links.txt
raptus.supersized.egg-info/entry_points.txt
raptus.supersized.egg-info/namespace_packages.txt
raptus.supersized.egg-info/not-zip-safe
raptus.supersized.egg-info/requires.txt
raptus.supersized.egg-info/top_level.txt
raptus/supersized/__init__.py
raptus/supersized/configure.zcml
raptus/supersized/browser/__init__.py
raptus/supersized/browser/back.png
raptus/supersized/browser/bg-black.png
raptus/supersized/browser/bg-hover.png
raptus/supersized/browser/button-tray-down.png
raptus/supersized/browser/button-tray-up.png
raptus/supersized/browser/configure.zcml
raptus/supersized/browser/forward.png
raptus/supersized/browser/nav-bg.png
raptus/supersized/browser/nav-dot.png
raptus/supersized/browser/pause.png
raptus/supersized/browser/play.png
raptus/supersized/browser/progress-back.png
raptus/supersized/browser/progress-bar.png
raptus/supersized/browser/progress.gif
raptus/supersized/browser/progress_.gif
raptus/supersized/browser/supersized.css
raptus/supersized/browser/supersized.init.js
raptus/supersized/browser/supersized.js
raptus/supersized/browser/thumb-back.png
raptus/supersized/browser/thumb-forward.png
raptus/supersized/profiles/default/cssregistry.xml
raptus/supersized/profiles/default/jsregistry.xml
raptus/supersized/profiles/default/metadata.xml
raptus/supersized/profiles/default/propertiestool.xml
raptus/supersized/profiles/default/skins.xml
raptus/supersized/skins/raptus_supersized/supersized.settings.js.py