Metadata-Version: 1.0
Name: raptus.supersized
Version: 1.0a1
Summary: Provides the supersized jQuery plugin integrated into Plone
Home-page: https://svn.plone.org/svn/collective/raptus.supersized
Author: Raptus AG
Author-email: dev@raptus.com
License: GPL
Platform: UNKNOWN
Classifier: Programming Language :: Python
Classifier: Topic :: Software Development :: Libraries :: Python Modules
